Metadata-Version: 2.1
Name: elasticsearch-query
Version: 2.3.0
Summary: Run queries against Kibana's Elasticsearch that gets logs from Logstash.
Home-page: https://github.com/macbre/elasticsearch-query
Author: Maciej Brencz
Author-email: macbre@wikia-inc.com
License: MIT
Keywords: logstash kibana elasticsearch logging
Platform: UNKNOWN
Provides-Extra: dev
